{"nodes": [{"id": "d_my_websites_mushroom_mushroom_pce_src_controllers_circuit_circuitpanelcontroller_ts", "label": "CircuitPanelController.ts", "file_type": "code", "source_file": "D:\\My Websites\\Mushroom\\mushroom-pce\\src\\controllers\\circuit\\CircuitPanelController.ts", "source_location": "L1"}, {"id": "circuitpanelcontroller_circuitpanel", "label": "CircuitPanel", "file_type": "code", "source_file": "D:\\My Websites\\Mushroom\\mushroom-pce\\src\\controllers\\circuit\\CircuitPanelController.ts", "source_location": "L7"}, {"id": "circuitpanelcontroller_circuitpanel_createorshow", "label": ".createOrShow()", "file_type": "code", "source_file": "D:\\My Websites\\Mushroom\\mushroom-pce\\src\\controllers\\circuit\\CircuitPanelController.ts", "source_location": "L32"}, {"id": "circuitpanelcontroller_circuitpanel_constructor", "label": ".constructor()", "file_type": "code", "source_file": "D:\\My Websites\\Mushroom\\mushroom-pce\\src\\controllers\\circuit\\CircuitPanelController.ts", "source_location": "L77"}, {"id": "circuitpanelcontroller_circuitpanel_dispose", "label": ".dispose()", "file_type": "code", "source_file": "D:\\My Websites\\Mushroom\\mushroom-pce\\src\\controllers\\circuit\\CircuitPanelController.ts", "source_location": "L200"}, {"id": "circuitpanelcontroller_circuitpanel_setgraph", "label": ".setGraph()", "file_type": "code", "source_file": "D:\\My Websites\\Mushroom\\mushroom-pce\\src\\controllers\\circuit\\CircuitPanelController.ts", "source_location": "L209"}, {"id": "circuitpanelcontroller_circuitpanel_openskeletonpanel", "label": ".openSkeletonPanel()", "file_type": "code", "source_file": "D:\\My Websites\\Mushroom\\mushroom-pce\\src\\controllers\\circuit\\CircuitPanelController.ts", "source_location": "L215"}, {"id": "circuitpanelcontroller_circuitpanel_gethtml", "label": ".getHtml()", "file_type": "code", "source_file": "D:\\My Websites\\Mushroom\\mushroom-pce\\src\\controllers\\circuit\\CircuitPanelController.ts", "source_location": "L256"}], "edges": [{"source": "d_my_websites_mushroom_mushroom_pce_src_controllers_circuit_circuitpanelcontroller_ts", "target": "vscode", "relation": "imports_from", "confidence": "EXTRACTED", "source_file": "D:\\My Websites\\Mushroom\\mushroom-pce\\src\\controllers\\circuit\\CircuitPanelController.ts", "source_location": "L1", "weight": 1.0}, {"source": "d_my_websites_mushroom_mushroom_pce_src_controllers_circuit_circuitpanelcontroller_ts", "target": "d_my_websites_mushroom_mushroom_pce_src_controllers_circuit_circuitdetailspanelcontroller", "relation": "imports_from", "confidence": "EXTRACTED", "source_file": "D:\\My Websites\\Mushroom\\mushroom-pce\\src\\controllers\\circuit\\CircuitPanelController.ts", "source_location": "L3", "weight": 1.0}, {"source": "d_my_websites_mushroom_mushroom_pce_src_controllers_circuit_circuitpanelcontroller_ts", "target": "d_my_websites_mushroom_mushroom_pce_src_shared_types_circuittypes", "relation": "imports_from", "confidence": "EXTRACTED", "source_file": "D:\\My Websites\\Mushroom\\mushroom-pce\\src\\controllers\\circuit\\CircuitPanelController.ts", "source_location": "L4", "weight": 1.0}, {"source": "d_my_websites_mushroom_mushroom_pce_src_controllers_circuit_circuitpanelcontroller_ts", "target": "d_my_websites_mushroom_mushroom_pce_src_views_circuit_circuitwebview", "relation": "imports_from", "confidence": "EXTRACTED", "source_file": "D:\\My Websites\\Mushroom\\mushroom-pce\\src\\controllers\\circuit\\CircuitPanelController.ts", "source_location": "L5", "weight": 1.0}, {"source": "d_my_websites_mushroom_mushroom_pce_src_controllers_circuit_circuitpanelcontroller_ts", "target": "circuitpanelcontroller_circuitpanel", "relation": "contains", "confidence": "EXTRACTED", "source_file": "D:\\My Websites\\Mushroom\\mushroom-pce\\src\\controllers\\circuit\\CircuitPanelController.ts", "source_location": "L7", "weight": 1.0}, {"source": "circuitpanelcontroller_circuitpanel", "target": "circuitpanelcontroller_circuitpanel_createorshow", "relation": "method", "confidence": "EXTRACTED", "source_file": "D:\\My Websites\\Mushroom\\mushroom-pce\\src\\controllers\\circuit\\CircuitPanelController.ts", "source_location": "L32", "weight": 1.0}, {"source": "circuitpanelcontroller_circuitpanel", "target": "circuitpanelcontroller_circuitpanel_constructor", "relation": "method", "confidence": "EXTRACTED", "source_file": "D:\\My Websites\\Mushroom\\mushroom-pce\\src\\controllers\\circuit\\CircuitPanelController.ts", "source_location": "L77", "weight": 1.0}, {"source": "circuitpanelcontroller_circuitpanel", "target": "circuitpanelcontroller_circuitpanel_dispose", "relation": "method", "confidence": "EXTRACTED", "source_file": "D:\\My Websites\\Mushroom\\mushroom-pce\\src\\controllers\\circuit\\CircuitPanelController.ts", "source_location": "L200", "weight": 1.0}, {"source": "circuitpanelcontroller_circuitpanel", "target": "circuitpanelcontroller_circuitpanel_setgraph", "relation": "method", "confidence": "EXTRACTED", "source_file": "D:\\My Websites\\Mushroom\\mushroom-pce\\src\\controllers\\circuit\\CircuitPanelController.ts", "source_location": "L209", "weight": 1.0}, {"source": "circuitpanelcontroller_circuitpanel", "target": "circuitpanelcontroller_circuitpanel_openskeletonpanel", "relation": "method", "confidence": "EXTRACTED", "source_file": "D:\\My Websites\\Mushroom\\mushroom-pce\\src\\controllers\\circuit\\CircuitPanelController.ts", "source_location": "L215", "weight": 1.0}, {"source": "circuitpanelcontroller_circuitpanel", "target": "circuitpanelcontroller_circuitpanel_gethtml", "relation": "method", "confidence": "EXTRACTED", "source_file": "D:\\My Websites\\Mushroom\\mushroom-pce\\src\\controllers\\circuit\\CircuitPanelController.ts", "source_location": "L256", "weight": 1.0}, {"source": "circuitpanelcontroller_circuitpanel_createorshow", "target": "circuitpanelcontroller_circuitpanel_setgraph", "relation": "calls", "confidence": "EXTRACTED", "source_file": "D:\\My Websites\\Mushroom\\mushroom-pce\\src\\controllers\\circuit\\CircuitPanelController.ts", "source_location": "L50", "weight": 1.0}, {"source": "circuitpanelcontroller_circuitpanel_constructor", "target": "circuitpanelcontroller_circuitpanel_gethtml", "relation": "calls", "confidence": "EXTRACTED", "source_file": "D:\\My Websites\\Mushroom\\mushroom-pce\\src\\controllers\\circuit\\CircuitPanelController.ts", "source_location": "L194", "weight": 1.0}], "raw_calls": [{"caller_nid": "circuitpanelcontroller_circuitpanel_createorshow", "callee": "reveal", "source_file": "D:\\My Websites\\Mushroom\\mushroom-pce\\src\\controllers\\circuit\\CircuitPanelController.ts", "source_location": "L49"}, {"caller_nid": "circuitpanelcontroller_circuitpanel_createorshow", "callee": "createWebviewPanel", "source_file": "D:\\My Websites\\Mushroom\\mushroom-pce\\src\\controllers\\circuit\\CircuitPanelController.ts", "source_location": "L54"}, {"caller_nid": "circuitpanelcontroller_circuitpanel_createorshow", "callee": "joinPath", "source_file": "D:\\My Websites\\Mushroom\\mushroom-pce\\src\\controllers\\circuit\\CircuitPanelController.ts", "source_location": "L58"}, {"caller_nid": "circuitpanelcontroller_circuitpanel_constructor", "callee": "onDidDispose", "source_file": "D:\\My Websites\\Mushroom\\mushroom-pce\\src\\controllers\\circuit\\CircuitPanelController.ts", "source_location": "L104"}, {"caller_nid": "circuitpanelcontroller_circuitpanel_constructor", "callee": "onDidReceiveMessage", "source_file": "D:\\My Websites\\Mushroom\\mushroom-pce\\src\\controllers\\circuit\\CircuitPanelController.ts", "source_location": "L105"}, {"caller_nid": "circuitpanelcontroller_circuitpanel_dispose", "callee": "pop", "source_file": "D:\\My Websites\\Mushroom\\mushroom-pce\\src\\controllers\\circuit\\CircuitPanelController.ts", "source_location": "L205"}, {"caller_nid": "circuitpanelcontroller_circuitpanel_setgraph", "callee": "postMessage", "source_file": "D:\\My Websites\\Mushroom\\mushroom-pce\\src\\controllers\\circuit\\CircuitPanelController.ts", "source_location": "L211"}, {"caller_nid": "circuitpanelcontroller_circuitpanel_setgraph", "callee": "syncGraph", "source_file": "D:\\My Websites\\Mushroom\\mushroom-pce\\src\\controllers\\circuit\\CircuitPanelController.ts", "source_location": "L212"}, {"caller_nid": "circuitpanelcontroller_circuitpanel_openskeletonpanel", "callee": "find", "source_file": "D:\\My Websites\\Mushroom\\mushroom-pce\\src\\controllers\\circuit\\CircuitPanelController.ts", "source_location": "L221"}, {"caller_nid": "circuitpanelcontroller_circuitpanel_openskeletonpanel", "callee": "onBuildSkeletonGraph", "source_file": "D:\\My Websites\\Mushroom\\mushroom-pce\\src\\controllers\\circuit\\CircuitPanelController.ts", "source_location": "L224"}, {"caller_nid": "circuitpanelcontroller_circuitpanel_openskeletonpanel", "callee": "createWebviewPanel", "source_file": "D:\\My Websites\\Mushroom\\mushroom-pce\\src\\controllers\\circuit\\CircuitPanelController.ts", "source_location": "L233"}, {"caller_nid": "circuitpanelcontroller_circuitpanel_openskeletonpanel", "callee": "joinPath", "source_file": "D:\\My Websites\\Mushroom\\mushroom-pce\\src\\controllers\\circuit\\CircuitPanelController.ts", "source_location": "L236"}, {"caller_nid": "circuitpanelcontroller_circuitpanel_gethtml", "callee": "buildCircuitPanelHtml", "source_file": "D:\\My Websites\\Mushroom\\mushroom-pce\\src\\controllers\\circuit\\CircuitPanelController.ts", "source_location": "L262"}]}