{"nodes": [{"id": "d_my_websites_mushroom_mushroom_pce_src_controllers_blueprint_blueprintpanelcontroller_ts", "label": "BlueprintPanelController.ts", "file_type": "code", "source_file": "D:\\My Websites\\Mushroom\\mushroom-pce\\src\\controllers\\blueprint\\BlueprintPanelController.ts", "source_location": "L1"}, {"id": "blueprintpanelcontroller_blueprintpanel", "label": "BlueprintPanel", "file_type": "code", "source_file": "D:\\My Websites\\Mushroom\\mushroom-pce\\src\\controllers\\blueprint\\BlueprintPanelController.ts", "source_location": "L24"}, {"id": "blueprintpanelcontroller_blueprintpanel_createorshow", "label": ".createOrShow()", "file_type": "code", "source_file": "D:\\My Websites\\Mushroom\\mushroom-pce\\src\\controllers\\blueprint\\BlueprintPanelController.ts", "source_location": "L34"}, {"id": "blueprintpanelcontroller_blueprintpanel_setgraphifycontextenabled", "label": ".setGraphifyContextEnabled()", "file_type": "code", "source_file": "D:\\My Websites\\Mushroom\\mushroom-pce\\src\\controllers\\blueprint\\BlueprintPanelController.ts", "source_location": "L72"}, {"id": "blueprintpanelcontroller_blueprintpanel_constructor", "label": ".constructor()", "file_type": "code", "source_file": "D:\\My Websites\\Mushroom\\mushroom-pce\\src\\controllers\\blueprint\\BlueprintPanelController.ts", "source_location": "L80"}, {"id": "blueprintpanelcontroller_blueprintpanel_dispose", "label": ".dispose()", "file_type": "code", "source_file": "D:\\My Websites\\Mushroom\\mushroom-pce\\src\\controllers\\blueprint\\BlueprintPanelController.ts", "source_location": "L122"}, {"id": "blueprintpanelcontroller_blueprintpanel_handleuserturn", "label": ".handleUserTurn()", "file_type": "code", "source_file": "D:\\My Websites\\Mushroom\\mushroom-pce\\src\\controllers\\blueprint\\BlueprintPanelController.ts", "source_location": "L131"}, {"id": "blueprintpanelcontroller_blueprintpanel_handlegenerateartifacts", "label": ".handleGenerateArtifacts()", "file_type": "code", "source_file": "D:\\My Websites\\Mushroom\\mushroom-pce\\src\\controllers\\blueprint\\BlueprintPanelController.ts", "source_location": "L146"}, {"id": "blueprintpanelcontroller_blueprintpanel_handlesaveartifacts", "label": ".handleSaveArtifacts()", "file_type": "code", "source_file": "D:\\My Websites\\Mushroom\\mushroom-pce\\src\\controllers\\blueprint\\BlueprintPanelController.ts", "source_location": "L162"}, {"id": "blueprintpanelcontroller_blueprintpanel_gethtml", "label": ".getHtml()", "file_type": "code", "source_file": "D:\\My Websites\\Mushroom\\mushroom-pce\\src\\controllers\\blueprint\\BlueprintPanelController.ts", "source_location": "L180"}, {"id": "blueprintpanelcontroller_normalizehistory", "label": "normalizeHistory()", "file_type": "code", "source_file": "D:\\My Websites\\Mushroom\\mushroom-pce\\src\\controllers\\blueprint\\BlueprintPanelController.ts", "source_location": "L771"}, {"id": "blueprintpanelcontroller_getnonce", "label": "getNonce()", "file_type": "code", "source_file": "D:\\My Websites\\Mushroom\\mushroom-pce\\src\\controllers\\blueprint\\BlueprintPanelController.ts", "source_location": "L783"}], "edges": [{"source": "d_my_websites_mushroom_mushroom_pce_src_controllers_blueprint_blueprintpanelcontroller_ts", "target": "vscode", "relation": "imports_from", "confidence": "EXTRACTED", "source_file": "D:\\My Websites\\Mushroom\\mushroom-pce\\src\\controllers\\blueprint\\BlueprintPanelController.ts", "source_location": "L1", "weight": 1.0}, {"source": "d_my_websites_mushroom_mushroom_pce_src_controllers_blueprint_blueprintpanelcontroller_ts", "target": "d_my_websites_mushroom_mushroom_pce_src_services_blueprint_generateblueprintcode", "relation": "imports_from", "confidence": "EXTRACTED", "source_file": "D:\\My Websites\\Mushroom\\mushroom-pce\\src\\controllers\\blueprint\\BlueprintPanelController.ts", "source_location": "L3", "weight": 1.0}, {"source": "d_my_websites_mushroom_mushroom_pce_src_controllers_blueprint_blueprintpanelcontroller_ts", "target": "blueprintpanelcontroller_blueprintpanel", "relation": "contains", "confidence": "EXTRACTED", "source_file": "D:\\My Websites\\Mushroom\\mushroom-pce\\src\\controllers\\blueprint\\BlueprintPanelController.ts", "source_location": "L24", "weight": 1.0}, {"source": "blueprintpanelcontroller_blueprintpanel", "target": "blueprintpanelcontroller_blueprintpanel_createorshow", "relation": "method", "confidence": "EXTRACTED", "source_file": "D:\\My Websites\\Mushroom\\mushroom-pce\\src\\controllers\\blueprint\\BlueprintPanelController.ts", "source_location": "L34", "weight": 1.0}, {"source": "blueprintpanelcontroller_blueprintpanel", "target": "blueprintpanelcontroller_blueprintpanel_setgraphifycontextenabled", "relation": "method", "confidence": "EXTRACTED", "source_file": "D:\\My Websites\\Mushroom\\mushroom-pce\\src\\controllers\\blueprint\\BlueprintPanelController.ts", "source_location": "L72", "weight": 1.0}, {"source": "blueprintpanelcontroller_blueprintpanel", "target": "blueprintpanelcontroller_blueprintpanel_constructor", "relation": "method", "confidence": "EXTRACTED", "source_file": "D:\\My Websites\\Mushroom\\mushroom-pce\\src\\controllers\\blueprint\\BlueprintPanelController.ts", "source_location": "L80", "weight": 1.0}, {"source": "blueprintpanelcontroller_blueprintpanel", "target": "blueprintpanelcontroller_blueprintpanel_dispose", "relation": "method", "confidence": "EXTRACTED", "source_file": "D:\\My Websites\\Mushroom\\mushroom-pce\\src\\controllers\\blueprint\\BlueprintPanelController.ts", "source_location": "L122", "weight": 1.0}, {"source": "blueprintpanelcontroller_blueprintpanel", "target": "blueprintpanelcontroller_blueprintpanel_handleuserturn", "relation": "method", "confidence": "EXTRACTED", "source_file": "D:\\My Websites\\Mushroom\\mushroom-pce\\src\\controllers\\blueprint\\BlueprintPanelController.ts", "source_location": "L131", "weight": 1.0}, {"source": "blueprintpanelcontroller_blueprintpanel", "target": "blueprintpanelcontroller_blueprintpanel_handlegenerateartifacts", "relation": "method", "confidence": "EXTRACTED", "source_file": "D:\\My Websites\\Mushroom\\mushroom-pce\\src\\controllers\\blueprint\\BlueprintPanelController.ts", "source_location": "L146", "weight": 1.0}, {"source": "blueprintpanelcontroller_blueprintpanel", "target": "blueprintpanelcontroller_blueprintpanel_handlesaveartifacts", "relation": "method", "confidence": "EXTRACTED", "source_file": "D:\\My Websites\\Mushroom\\mushroom-pce\\src\\controllers\\blueprint\\BlueprintPanelController.ts", "source_location": "L162", "weight": 1.0}, {"source": "blueprintpanelcontroller_blueprintpanel", "target": "blueprintpanelcontroller_blueprintpanel_gethtml", "relation": "method", "confidence": "EXTRACTED", "source_file": "D:\\My Websites\\Mushroom\\mushroom-pce\\src\\controllers\\blueprint\\BlueprintPanelController.ts", "source_location": "L180", "weight": 1.0}, {"source": "d_my_websites_mushroom_mushroom_pce_src_controllers_blueprint_blueprintpanelcontroller_ts", "target": "blueprintpanelcontroller_normalizehistory", "relation": "contains", "confidence": "EXTRACTED", "source_file": "D:\\My Websites\\Mushroom\\mushroom-pce\\src\\controllers\\blueprint\\BlueprintPanelController.ts", "source_location": "L771", "weight": 1.0}, {"source": "d_my_websites_mushroom_mushroom_pce_src_controllers_blueprint_blueprintpanelcontroller_ts", "target": "blueprintpanelcontroller_getnonce", "relation": "contains", "confidence": "EXTRACTED", "source_file": "D:\\My Websites\\Mushroom\\mushroom-pce\\src\\controllers\\blueprint\\BlueprintPanelController.ts", "source_location": "L783", "weight": 1.0}, {"source": "blueprintpanelcontroller_blueprintpanel_constructor", "target": "blueprintpanelcontroller_blueprintpanel_gethtml", "relation": "calls", "confidence": "EXTRACTED", "source_file": "D:\\My Websites\\Mushroom\\mushroom-pce\\src\\controllers\\blueprint\\BlueprintPanelController.ts", "source_location": "L93", "weight": 1.0}, {"source": "blueprintpanelcontroller_blueprintpanel_gethtml", "target": "blueprintpanelcontroller_getnonce", "relation": "calls", "confidence": "EXTRACTED", "source_file": "D:\\My Websites\\Mushroom\\mushroom-pce\\src\\controllers\\blueprint\\BlueprintPanelController.ts", "source_location": "L181", "weight": 1.0}], "raw_calls": [{"caller_nid": "blueprintpanelcontroller_blueprintpanel_createorshow", "callee": "postMessage", "source_file": "D:\\My Websites\\Mushroom\\mushroom-pce\\src\\controllers\\blueprint\\BlueprintPanelController.ts", "source_location": "L43"}, {"caller_nid": "blueprintpanelcontroller_blueprintpanel_createorshow", "callee": "reveal", "source_file": "D:\\My Websites\\Mushroom\\mushroom-pce\\src\\controllers\\blueprint\\BlueprintPanelController.ts", "source_location": "L48"}, {"caller_nid": "blueprintpanelcontroller_blueprintpanel_createorshow", "callee": "createWebviewPanel", "source_file": "D:\\My Websites\\Mushroom\\mushroom-pce\\src\\controllers\\blueprint\\BlueprintPanelController.ts", "source_location": "L52"}, {"caller_nid": "blueprintpanelcontroller_blueprintpanel_setgraphifycontextenabled", "callee": "postMessage", "source_file": "D:\\My Websites\\Mushroom\\mushroom-pce\\src\\controllers\\blueprint\\BlueprintPanelController.ts", "source_location": "L77"}, {"caller_nid": "blueprintpanelcontroller_blueprintpanel_constructor", "callee": "Boolean", "source_file": "D:\\My Websites\\Mushroom\\mushroom-pce\\src\\controllers\\blueprint\\BlueprintPanelController.ts", "source_location": "L91"}, {"caller_nid": "blueprintpanelcontroller_blueprintpanel_constructor", "callee": "onDidReceiveMessage", "source_file": "D:\\My Websites\\Mushroom\\mushroom-pce\\src\\controllers\\blueprint\\BlueprintPanelController.ts", "source_location": "L94"}, {"caller_nid": "blueprintpanelcontroller_blueprintpanel_constructor", "callee": "onDidDispose", "source_file": "D:\\My Websites\\Mushroom\\mushroom-pce\\src\\controllers\\blueprint\\BlueprintPanelController.ts", "source_location": "L119"}, {"caller_nid": "blueprintpanelcontroller_blueprintpanel_dispose", "callee": "pop", "source_file": "D:\\My Websites\\Mushroom\\mushroom-pce\\src\\controllers\\blueprint\\BlueprintPanelController.ts", "source_location": "L127"}, {"caller_nid": "blueprintpanelcontroller_blueprintpanel_handleuserturn", "callee": "onUserTurn", "source_file": "D:\\My Websites\\Mushroom\\mushroom-pce\\src\\controllers\\blueprint\\BlueprintPanelController.ts", "source_location": "L133"}, {"caller_nid": "blueprintpanelcontroller_blueprintpanel_handleuserturn", "callee": "postMessage", "source_file": "D:\\My Websites\\Mushroom\\mushroom-pce\\src\\controllers\\blueprint\\BlueprintPanelController.ts", "source_location": "L134"}, {"caller_nid": "blueprintpanelcontroller_blueprintpanel_handleuserturn", "callee": "postMessage", "source_file": "D:\\My Websites\\Mushroom\\mushroom-pce\\src\\controllers\\blueprint\\BlueprintPanelController.ts", "source_location": "L139"}, {"caller_nid": "blueprintpanelcontroller_blueprintpanel_handleuserturn", "callee": "String", "source_file": "D:\\My Websites\\Mushroom\\mushroom-pce\\src\\controllers\\blueprint\\BlueprintPanelController.ts", "source_location": "L141"}, {"caller_nid": "blueprintpanelcontroller_blueprintpanel_handlegenerateartifacts", "callee": "onGenerateArtifacts", "source_file": "D:\\My Websites\\Mushroom\\mushroom-pce\\src\\controllers\\blueprint\\BlueprintPanelController.ts", "source_location": "L148"}, {"caller_nid": "blueprintpanelcontroller_blueprintpanel_handlegenerateartifacts", "callee": "postMessage", "source_file": "D:\\My Websites\\Mushroom\\mushroom-pce\\src\\controllers\\blueprint\\BlueprintPanelController.ts", "source_location": "L150"}, {"caller_nid": "blueprintpanelcontroller_blueprintpanel_handlegenerateartifacts", "callee": "postMessage", "source_file": "D:\\My Websites\\Mushroom\\mushroom-pce\\src\\controllers\\blueprint\\BlueprintPanelController.ts", "source_location": "L155"}, {"caller_nid": "blueprintpanelcontroller_blueprintpanel_handlegenerateartifacts", "callee": "String", "source_file": "D:\\My Websites\\Mushroom\\mushroom-pce\\src\\controllers\\blueprint\\BlueprintPanelController.ts", "source_location": "L157"}, {"caller_nid": "blueprintpanelcontroller_blueprintpanel_handlesaveartifacts", "callee": "onSaveArtifacts", "source_file": "D:\\My Websites\\Mushroom\\mushroom-pce\\src\\controllers\\blueprint\\BlueprintPanelController.ts", "source_location": "L164"}, {"caller_nid": "blueprintpanelcontroller_blueprintpanel_handlesaveartifacts", "callee": "postMessage", "source_file": "D:\\My Websites\\Mushroom\\mushroom-pce\\src\\controllers\\blueprint\\BlueprintPanelController.ts", "source_location": "L165"}, {"caller_nid": "blueprintpanelcontroller_blueprintpanel_handlesaveartifacts", "callee": "postMessage", "source_file": "D:\\My Websites\\Mushroom\\mushroom-pce\\src\\controllers\\blueprint\\BlueprintPanelController.ts", "source_location": "L170"}, {"caller_nid": "blueprintpanelcontroller_blueprintpanel_handlesaveartifacts", "callee": "String", "source_file": "D:\\My Websites\\Mushroom\\mushroom-pce\\src\\controllers\\blueprint\\BlueprintPanelController.ts", "source_location": "L174"}, {"caller_nid": "blueprintpanelcontroller_blueprintpanel_gethtml", "callee": "stringify", "source_file": "D:\\My Websites\\Mushroom\\mushroom-pce\\src\\controllers\\blueprint\\BlueprintPanelController.ts", "source_location": "L183"}, {"caller_nid": "blueprintpanelcontroller_normalizehistory", "callee": "isArray", "source_file": "D:\\My Websites\\Mushroom\\mushroom-pce\\src\\controllers\\blueprint\\BlueprintPanelController.ts", "source_location": "L772"}, {"caller_nid": "blueprintpanelcontroller_normalizehistory", "callee": "filter", "source_file": "D:\\My Websites\\Mushroom\\mushroom-pce\\src\\controllers\\blueprint\\BlueprintPanelController.ts", "source_location": "L775"}, {"caller_nid": "blueprintpanelcontroller_normalizehistory", "callee": "map", "source_file": "D:\\My Websites\\Mushroom\\mushroom-pce\\src\\controllers\\blueprint\\BlueprintPanelController.ts", "source_location": "L775"}, {"caller_nid": "blueprintpanelcontroller_getnonce", "callee": "charAt", "source_file": "D:\\My Websites\\Mushroom\\mushroom-pce\\src\\controllers\\blueprint\\BlueprintPanelController.ts", "source_location": "L787"}, {"caller_nid": "blueprintpanelcontroller_getnonce", "callee": "floor", "source_file": "D:\\My Websites\\Mushroom\\mushroom-pce\\src\\controllers\\blueprint\\BlueprintPanelController.ts", "source_location": "L787"}, {"caller_nid": "blueprintpanelcontroller_getnonce", "callee": "random", "source_file": "D:\\My Websites\\Mushroom\\mushroom-pce\\src\\controllers\\blueprint\\BlueprintPanelController.ts", "source_location": "L787"}]}